dlrs/__init__.py
dlrs/py.typed
dlrs/scheduler.py
dlrs/utils.py
pytorch_dlrs-0.2.1.dist-info/licenses/LICENSE
pytorch_dlrs-0.2.1.dist-info/METADATA
pytorch_dlrs-0.2.1.dist-info/WHEEL
pytorch_dlrs-0.2.1.dist-info/top_level.txt
pytorch_dlrs-0.2.1.dist-info/RECORD
