Metadata-Version: 2.4
Name: pytorch-dlrs
Version: 0.2.1
Summary: Dynamic Learning Rate Scheduler for PyTorch
Home-page: https://github.com/Thabhelo/pytorch-dlrs
Author: Thabhelo
Author-email: Thabhelo <thabhelo@deepubuntu.com>
Maintainer-email: Thabhelo <thabhelo@deepubuntu.com>
License: MIT
Project-URL: Homepage, https://github.com/Thabhelo/pytorch-dlrs
Project-URL: Documentation, https://github.com/Thabhelo/pytorch-dlrs/blob/main/README.md
Project-URL: Repository, https://github.com/Thabhelo/pytorch-dlrs
Project-URL: Issues, https://github.com/Thabhelo/pytorch-dlrs/issues
Keywords: pytorch,deep-learning,machine-learning,learning-rate,scheduler,optimization
Classifier: Development Status :: 3 - Alpha
Classifier: Intended Audience :: Developers
Classifier: Intended Audience :: Science/Research
Classifier: Programming Language :: Python :: 3
Classifier: Programming Language :: Python :: 3.8
Classifier: Programming Language :: Python :: 3.9
Classifier: Programming Language :: Python :: 3.10
Classifier: Programming Language :: Python :: 3.11
Classifier: Programming Language :: Python :: 3.12
Classifier: Topic :: Scientific/Engineering :: Artificial Intelligence
Classifier: Topic :: Software Development :: Libraries :: Python Modules
Requires-Python: >=3.8
License-File: LICENSE
Requires-Dist: torch>=2.0.0
Requires-Dist: numpy>=1.21.0
Provides-Extra: dev
Requires-Dist: pytest>=7.0.0; extra == "dev"
Requires-Dist: pytest-cov>=4.0.0; extra == "dev"
Requires-Dist: ruff>=0.1.0; extra == "dev"
Requires-Dist: mypy>=1.0.0; extra == "dev"
Dynamic: author
Dynamic: home-page
Dynamic: license-file
Dynamic: requires-python
